{"cameraMode":{"drawMode":0,"name":"Shaded","section":"Shading Mode"},"sceneLighting":true,"audioPlay":false,"sceneViewState":{"showFog":true,"showMaterialUpdate":false,"showSkybox":true,"showFlares":true,"showImageEffects":true,"showParticleSystems":true},"in2DMode":false,"pivot":{"x":-13.723941802978516,"y":0.6873235702514648,"z":-5.103916168212891},"rotation":{"x":-0.024716682732105256,"y":-0.9425137042999268,"z":0.0704483613371849,"w":-0.3261205554008484},"size":29.479860305786134,"orthographic":false}